[
    {
        "_id": 1001,
        "dob_9": "2011-08-14",
        "dob_10": "2011-07-31",
        "dob_8": "2013-03-15",
        "dob_7": "2010-09-10",
        "dob_6": "2011-02-10"
    },
    {
        "_id": 101,
        "name": "Chris",
        "age": 15,
        "dob": "2009-04-05",
        "gender": "male"
    },
    {
        "_id": 102,
        "name": "Kenneth",
        "age": 6,
        "dob": "2017-09-11",
        "gender": "female"
    },
    {
        "_id": 103,
        "name": "Veronica",
        "age": 11,
        "dob": "2012-11-16",
        "gender": "female"
    },
    {
        "_id": 104,
        "name": "Mallory",
        "age": 5,
        "dob": "2019-07-22",
        "gender": "female"
    },
    {
        "_id": 105,
        "name": "Melissa",
        "age": 15,
        "dob": "2009-06-22",
        "gender": "male"
    },
    {
        "_id": 106,
        "name": "Richard",
        "age": 13,
        "gender": "female"
    },
    {
        "_id": 107,
        "name": "Deborah",
        "age": 13,
        "gender": "male"
    },
    {
        "_id": 108,
        "name": "Diane",
        "age": 11,
        "gender": "female"
    },
    {
        "_id": 109,
        "name": "Wayne",
        "age": 12,
        "gender": "female"
    },
    {
        "_id": 110,
        "name": "Jason",
        "age": 12,
        "gender": "male"
    }
]